Metadata-Version: 1.0
Name: rg51318locationsfromwebservices
Version: 1.0
Summary: rg51318locationsfromwebservices
Home-page: http://drupal.psu.edu/geog489/
Author: GEOG489
Author-email: GEOG489@psu.edu
License: BSD
Platform: UNKNOWN
